{"packages":{"ircmaxell/random-lib":{"1.0.x-dev":{"name":"ircmaxell/random-lib","description":"A Library For Generating Secure Random Numbers","keywords":["cryptography","random","random-numbers","random-strings"],"homepage":"https://github.com/ircmaxell/RandomLib","version":"1.0.x-dev","version_normalized":"1.0.9999999.9999999-dev","license":["MIT"],"authors":[{"name":"Anthony Ferrara","email":"ircmaxell@ircmaxell.com","homepage":"http://blog.ircmaxell.com"}],"source":{"url":"https://github.com/ircmaxell/RandomLib.git","type":"git","reference":"e9e0204f40e49fa4419946c677eccd3fa25b8cf4"},"dist":{"url":"https://api.github.com/repos/ircmaxell/RandomLib/zipball/e9e0204f40e49fa4419946c677eccd3fa25b8cf4","type":"zip","shasum":"","reference":"e9e0204f40e49fa4419946c677eccd3fa25b8cf4"},"type":"library","time":"2016-09-07T15:52:06+00:00","autoload":{"psr-0":{"RandomLib":"lib"}},"extra":{"branch-alias":{"dev-master":"1.1.x-dev"}},"require":{"php":">=5.3.2","ircmaxell/security-lib":"^1.1"},"require-dev":{"mikey179/vfsstream":"^1.6","friendsofphp/php-cs-fixer":"^1.11","phpunit/phpunit":"^4.8|^5.0"},"uid":306744},"dev-cipher_mixer":{"name":"ircmaxell/random-lib","description":"A Library For Generating Secure Random Numbers","keywords":["cryptography","random","random-numbers","random-strings"],"homepage":"https://github.com/ircmaxell/RandomLib","version":"dev-cipher_mixer","version_normalized":"dev-cipher_mixer","license":["MIT"],"authors":[{"name":"Anthony Ferrara","email":"ircmaxell@ircmaxell.com","homepage":"http://blog.ircmaxell.com"}],"source":{"url":"https://github.com/ircmaxell/RandomLib.git","type":"git","reference":"4439c51191080ebffdd4c51a95bab5e98e8a622f"},"dist":{"url":"https://api.github.com/repos/ircmaxell/RandomLib/zipball/4439c51191080ebffdd4c51a95bab5e98e8a622f","type":"zip","shasum":"","reference":"4439c51191080ebffdd4c51a95bab5e98e8a622f"},"type":"library","time":"2014-04-11T18:23:00+00:00","autoload":{"psr-0":{"RandomLib":"lib"}},"extra":{"branch-alias":{"dev-master":"1.0.x-dev"}},"require":{"ircmaxell/security-lib":"1.0.*@dev","php":">=5.3.2"},"require-dev":{"mikey179/vfsstream":"1.1.*","phpunit/phpunit":"3.7.*"},"uid":157831},"dev-improved_string_presets":{"name":"ircmaxell/random-lib","description":"A Library For Generating Secure Random Numbers","keywords":["cryptography","random","random-numbers","random-strings"],"homepage":"https://github.com/ircmaxell/RandomLib","version":"dev-improved_string_presets","version_normalized":"dev-improved_string_presets","license":["MIT"],"authors":[{"name":"Anthony Ferrara","email":"ircmaxell@ircmaxell.com","homepage":"http://blog.ircmaxell.com"}],"source":{"url":"https://github.com/ircmaxell/RandomLib.git","type":"git","reference":"90fc8a94fc1f2deb3502b2b9dd9fd20dfcbb1dc2"},"dist":{"url":"https://api.github.com/repos/ircmaxell/RandomLib/zipball/90fc8a94fc1f2deb3502b2b9dd9fd20dfcbb1dc2","type":"zip","shasum":"","reference":"90fc8a94fc1f2deb3502b2b9dd9fd20dfcbb1dc2"},"type":"library","time":"2014-05-01T12:31:29+00:00","autoload":{"psr-0":{"RandomLib":"lib"}},"extra":{"branch-alias":{"dev-master":"1.0.x-dev"}},"require":{"ircmaxell/security-lib":"1.0.*@dev","php":">=5.3.2"},"require-dev":{"mikey179/vfsstream":"1.1.*","phpunit/phpunit":"3.7.*"},"uid":157882},"v1.0.0":{"name":"ircmaxell/random-lib","description":"A Library For Generating Secure Random Numbers","keywords":["cryptography","random","random-numbers","random-strings"],"homepage":"https://github.com/ircmaxell/PHP-RandomLib","version":"v1.0.0","version_normalized":"1.0.0.0","license":["MIT"],"authors":[{"name":"Anthony Ferrara","email":"ircmaxell@ircmaxell.com","homepage":"http://blog.ircmaxell.com"}],"source":{"url":"https://github.com/ircmaxell/RandomLib.git","type":"git","reference":"0eaad991c1756842f26dfbcbc6effcabb5003d0a"},"dist":{"url":"https://api.github.com/repos/ircmaxell/RandomLib/zipball/0eaad991c1756842f26dfbcbc6effcabb5003d0a","type":"zip","shasum":"","reference":"0eaad991c1756842f26dfbcbc6effcabb5003d0a"},"type":"library","time":"2013-07-30T17:40:57+00:00","autoload":{"psr-0":{"RandomLib":"lib"}},"extra":{"branch-alias":{"dev-master":"1.0.x-dev"}},"require":{"ircmaxell/security-lib":"1.0.*@dev","php":">=5.3.2"},"require-dev":{"mikey179/vfsstream":"1.1.*"},"uid":72930},"v1.1.0":{"name":"ircmaxell/random-lib","description":"A Library For Generating Secure Random Numbers","keywords":["cryptography","random","random-numbers","random-strings"],"homepage":"https://github.com/ircmaxell/RandomLib","version":"v1.1.0","version_normalized":"1.1.0.0","license":["MIT"],"authors":[{"name":"Anthony Ferrara","email":"ircmaxell@ircmaxell.com","homepage":"http://blog.ircmaxell.com"}],"source":{"url":"https://github.com/ircmaxell/RandomLib.git","type":"git","reference":"13efa4368bb2ac88bb3b1459b487d907de4dbf7c"},"dist":{"url":"https://api.github.com/repos/ircmaxell/RandomLib/zipball/13efa4368bb2ac88bb3b1459b487d907de4dbf7c","type":"zip","shasum":"","reference":"13efa4368bb2ac88bb3b1459b487d907de4dbf7c"},"type":"library","time":"2015-01-15T16:31:45+00:00","autoload":{"psr-0":{"RandomLib":"lib"}},"extra":{"branch-alias":{"dev-master":"1.0.x-dev"}},"require":{"ircmaxell/security-lib":"1.0.*@dev","php":">=5.3.2"},"require-dev":{"mikey179/vfsstream":"1.1.*","phpunit/phpunit":"3.7.*"},"uid":306745},"v1.2.0":{"name":"ircmaxell/random-lib","description":"A Library For Generating Secure Random Numbers","keywords":["cryptography","random","random-numbers","random-strings"],"homepage":"https://github.com/ircmaxell/RandomLib","version":"v1.2.0","version_normalized":"1.2.0.0","license":["MIT"],"authors":[{"name":"Anthony Ferrara","email":"ircmaxell@ircmaxell.com","homepage":"http://blog.ircmaxell.com"}],"source":{"url":"https://github.com/ircmaxell/RandomLib.git","type":"git","reference":"e9e0204f40e49fa4419946c677eccd3fa25b8cf4"},"dist":{"url":"https://api.github.com/repos/ircmaxell/RandomLib/zipball/e9e0204f40e49fa4419946c677eccd3fa25b8cf4","type":"zip","shasum":"","reference":"e9e0204f40e49fa4419946c677eccd3fa25b8cf4"},"type":"library","time":"2016-09-07T15:52:06+00:00","autoload":{"psr-0":{"RandomLib":"lib"}},"extra":{"branch-alias":{"dev-master":"1.1.x-dev"}},"require":{"ircmaxell/security-lib":"^1.1","php":">=5.3.2"},"require-dev":{"mikey179/vfsstream":"^1.6","friendsofphp/php-cs-fixer":"^1.11","phpunit/phpunit":"^4.8|^5.0"},"uid":983521}}}}